        
[
  {
    "patchName": "Custom branding name YouTube",
    "options": [
      {
        "key": "AppName",
        "value": "YouTube"
      }
    ]
  },
  {
    "patchName": "Custom branding icon YouTube",
    "options": [
      {
        "key": "AppIcon",
        "value": "red"
      }
    ]
  },
  {
    "patchName": "Theme",
    "options": [
      {
        "key": "DarkThemeBackgroundColor",
        "value": "@android:color/black"
      },
      {
        "key": "LightThemeBackgroundColor",
        "value": "@android:color/white"
      }
    ]
  }
]
        
